yirifi_mcp/__init__.py
yirifi_mcp/catalog/__init__.py
yirifi_mcp/catalog/base.py
yirifi_mcp/catalog/policy.py
yirifi_mcp/catalog/reg_service.py
yirifi_mcp/catalog/risk_service.py
yirifi_mcp/catalog/spec_driven.py
yirifi_mcp/catalog/overrides/__init__.py
yirifi_mcp/catalog/overrides/agents.py
yirifi_mcp/catalog/overrides/auth.py
yirifi_mcp/catalog/overrides/reg.py
yirifi_mcp/catalog/overrides/risk.py
yirifi_mcp/cli/__init__.py
yirifi_mcp/cli/dynamic_choice.py
yirifi_mcp/cli/main.py
yirifi_mcp/cli/scaffold.py
yirifi_mcp/core/__init__.py
yirifi_mcp/core/config.py
yirifi_mcp/core/decorators.py
yirifi_mcp/core/environment_middleware.py
yirifi_mcp/core/exceptions.py
yirifi_mcp/core/http_client.py
yirifi_mcp/core/middleware.py
yirifi_mcp/core/observability.py
yirifi_mcp/core/openapi_utils.py
yirifi_mcp/core/protocols.py
yirifi_mcp/core/resilience.py
yirifi_mcp/core/response_wrapper.py
yirifi_mcp/core/route_filters.py
yirifi_mcp/core/scope.py
yirifi_mcp/core/scope_filter_middleware.py
yirifi_mcp/core/scope_middleware.py
yirifi_mcp/core/service_descriptor.py
yirifi_mcp/core/shutdown.py
yirifi_mcp/core/tool_optimizer.py
yirifi_mcp/core/toon_encoder.py
yirifi_mcp/core/transport.py
yirifi_mcp/core/unified_registry.py
yirifi_mcp/core/validation.py
yirifi_mcp/gateway/__init__.py
yirifi_mcp/gateway/base.py
yirifi_mcp/gateway/dynamic.py
yirifi_mcp/server/__init__.py
yirifi_mcp/server/factory.py
yirifi_mcp/server/http.py
yirifi_mcp/server/multi_service.py
yirifi_mcp/servers/__init__.py
yirifi_mcp/servers/agents_service/__init__.py
yirifi_mcp/servers/agents_service/server.py
yirifi_mcp/servers/auth_service/__init__.py
yirifi_mcp/servers/auth_service/server.py
yirifi_mcp/servers/reg_service/__init__.py
yirifi_mcp/servers/reg_service/server.py
yirifi_mcp/servers/risk_service/__init__.py
yirifi_mcp/servers/risk_service/server.py
yirifi_ops_mcp_hub-0.5.0.dist-info/METADATA
yirifi_ops_mcp_hub-0.5.0.dist-info/WHEEL
yirifi_ops_mcp_hub-0.5.0.dist-info/entry_points.txt
yirifi_ops_mcp_hub-0.5.0.dist-info/top_level.txt
yirifi_ops_mcp_hub-0.5.0.dist-info/RECORD
