Metadata-Version: 2.4
Name: yirifi-ops-mcp-hub
Version: 0.5.0
Summary: MCP servers for Yirifi Ops - expose REST APIs as MCP tools for AI assistants
Author-email: Yirifi <dev@yirifi.ai>
License-Expression: LicenseRef-Proprietary
Project-URL: Homepage, https://github.com/yirifi/yirifi-ops-mcp-hub
Project-URL: Repository, https://github.com/yirifi/yirifi-ops-mcp-hub
Project-URL: Issues, https://github.com/yirifi/yirifi-ops-mcp-hub/issues
Keywords: mcp,model-context-protocol,fastmcp,ai,llm,claude
Classifier: Development Status :: 4 - Beta
Classifier: Intended Audience :: Developers
Classifier: Programming Language :: Python :: 3
Classifier: Programming Language :: Python :: 3.11
Classifier: Programming Language :: Python :: 3.12
Classifier: Topic :: Software Development :: Libraries :: Python Modules
Requires-Python: >=3.11
Requires-Dist: fastmcp>=2.0
Requires-Dist: httpx>=0.27
Requires-Dist: pydantic>=2.0
Requires-Dist: pydantic-settings>=2.0
Requires-Dist: python-dotenv>=1.0
Requires-Dist: click>=8.0
Requires-Dist: structlog>=24.0
Requires-Dist: uvicorn[standard]>=0.30
Requires-Dist: starlette>=0.38
Requires-Dist: aiolimiter>=1.1.0
Requires-Dist: tenacity>=8.2.0
Requires-Dist: toon-format>=0.1.0
Provides-Extra: dev
Requires-Dist: pytest>=8.0; extra == "dev"
Requires-Dist: pytest-asyncio>=0.23; extra == "dev"
Requires-Dist: pytest-cov>=4.0; extra == "dev"
Requires-Dist: ruff>=0.1; extra == "dev"
Requires-Dist: mypy>=1.8; extra == "dev"
